nvos/__init__.py
nvos/file.py
nvos/remote.py
nvos/run.py
skyeye/__init__.py
skyeye/handler.py
skyeye/loghandler.py
skyeye/remote.py
start/__init__.py
start/log.py
start/login.py
start/main.py
start/utils.py
win/win_auto_script.py
nvosscript-1.3.7.8.dist-info/LICENSE
nvosscript-1.3.7.8.dist-info/METADATA
nvosscript-1.3.7.8.dist-info/WHEEL
nvosscript-1.3.7.8.dist-info/entry_points.txt
nvosscript-1.3.7.8.dist-info/top_level.txt
nvosscript-1.3.7.8.dist-info/RECORD
