Metadata-Version: 2.1
Name: nvosscript
Version: 1.3.7.8
Summary: nvos toolchain script
Author: andre.zhao
Author-email: andre.zhao@nio.com
License: MIT
Keywords: pack
Classifier: Programming Language :: Python :: 3
Classifier: License :: OSI Approved :: MIT License
Classifier: Operating System :: OS Independent
License-File: LICENSE
Requires-Dist: requests
Requires-Dist: python-daemon
Requires-Dist: boto3
Requires-Dist: ldap3
Requires-Dist: daemon
Requires-Dist: tqdm
